<annotation verified="Yes">
    <folder>images</folder>
    <filename>frame_00850.png</filename>
    <source>
        <database>Unknown</database>
    </source>
    <size>
        <width>1920</width>
        <height>1080</height>
        <depth>3</depth>
    </size>
    <segmented>0</segmented>
    <object>
        <name>Pedestrian</name>
        <pose>Unspecified</pose>
        <truncated>0</truncated>
        <difficult>0</difficult>
        <bndbox>
            <xmin>1373.0</xmin>
            <ymin>240.0</ymin>
            <xmax>1370.0</xmax>
            <ymax>240.0</ymax>
        </bndbox>
    </object>
    <object>
        <name>Pedestrian</name>
        <pose>Unspecified</pose>
        <truncated>0</truncated>
        <difficult>0</difficult>
        <bndbox>
            <xmin>1039.0</xmin>
            <ymin>489.0</ymin>
            <xmax>1036.0</xmax>
            <ymax>493.0</ymax>
        </bndbox>
    </object>
    <object>
        <name>Pedestrian</name>
        <pose>Unspecified</pose>
        <truncated>0</truncated>
        <difficult>0</difficult>
        <bndbox>
            <xmin>703.0</xmin>
            <ymin>217.0</ymin>
            <xmax>707.0</xmax>
            <ymax>221.0</ymax>
        </bndbox>
    </object>
    <object>
        <name>Pedestrian</name>
        <pose>Unspecified</pose>
        <truncated>0</truncated>
        <difficult>0</difficult>
        <bndbox>
            <xmin>952.0</xmin>
            <ymin>555.0</ymin>
            <xmax>955.0</xmax>
            <ymax>556.0</ymax>
        </bndbox>
    </object>
    <object>
        <name>Car</name>
        <pose>Unspecified</pose>
        <truncated>0</truncated>
        <difficult>0</difficult>
        <bndbox>
            <xmin>1504.0</xmin>
            <ymin>148.0</ymin>
            <xmax>1512.0</xmax>
            <ymax>143.0</ymax>
        </bndbox>
    </object>
    <object>
        <name>Pedestrian</name>
        <pose>Unspecified</pose>
        <truncated>0</truncated>
        <difficult>0</difficult>
        <bndbox>
            <xmin>1573.0</xmin>
            <ymin>471.0</ymin>
            <xmax>1573.0</xmax>
            <ymax>477.0</ymax>
        </bndbox>
    </object>
    <object>
        <name>Pedestrian</name>
        <pose>Unspecified</pose>
        <truncated>0</truncated>
        <difficult>0</difficult>
        <bndbox>
            <xmin>1875.0</xmin>
            <ymin>23.0</ymin>
            <xmax>1873.0</xmax>
            <ymax>28.0</ymax>
        </bndbox>
    </object>
    <object>
        <name>Car</name>
        <pose>Unspecified</pose>
        <truncated>0</truncated>
        <difficult>0</difficult>
        <bndbox>
            <xmin>1826.0</xmin>
            <ymin>1.0</ymin>
            <xmax>1822.0</xmax>
            <ymax>11.0</ymax>
        </bndbox>
    </object>
    <object>
        <name>Car</name>
        <pose>Unspecified</pose>
        <truncated>0</truncated>
        <difficult>0</difficult>
        <bndbox>
            <xmin>1916.0</xmin>
            <ymin>191.0</ymin>
            <xmax>1919.0</xmax>
            <ymax>209.0</ymax>
        </bndbox>
    </object>
    <object>
        <name>Car</name>
        <pose>Unspecified</pose>
        <truncated>0</truncated>
        <difficult>0</difficult>
        <bndbox>
            <xmin>1608.0</xmin>
            <ymin>68.0</ymin>
            <xmax>1599.0</xmax>
            <ymax>64.0</ymax>
        </bndbox>
    </object>
    <object>
        <name>Car</name>
        <pose>Unspecified</pose>
        <truncated>0</truncated>
        <difficult>0</difficult>
        <bndbox>
            <xmin>1763.0</xmin>
            <ymin>1.0</ymin>
            <xmax>1781.0</xmax>
            <ymax>0.0</ymax>
        </bndbox>
    </object>
    <object>
        <name>Car</name>
        <pose>Unspecified</pose>
        <truncated>0</truncated>
        <difficult>0</difficult>
        <bndbox>
            <xmin>1526.0</xmin>
            <ymin>48.0</ymin>
            <xmax>1527.0</xmax>
            <ymax>64.0</ymax>
        </bndbox>
    </object>
    <object>
        <name>Car</name>
        <pose>Unspecified</pose>
        <truncated>0</truncated>
        <difficult>0</difficult>
        <bndbox>
            <xmin>1642.0</xmin>
            <ymin>1.0</ymin>
            <xmax>1652.0</xmax>
            <ymax>38.0</ymax>
        </bndbox>
    </object>
    <object>
        <name>Car</name>
        <pose>Unspecified</pose>
        <truncated>0</truncated>
        <difficult>0</difficult>
        <bndbox>
            <xmin>1813.0</xmin>
            <ymin>992.0</ymin>
            <xmax>1825.0</xmax>
            <ymax>991.0</ymax>
        </bndbox>
    </object>
    <object>
        <name>Car</name>
        <pose>Unspecified</pose>
        <truncated>0</truncated>
        <difficult>0</difficult>
        <bndbox>
            <xmin>683.0</xmin>
            <ymin>746.0</ymin>
            <xmax>690.0</xmax>
            <ymax>743.0</ymax>
        </bndbox>
    </object>
    <object>
        <name>Car</name>
        <pose>Unspecified</pose>
        <truncated>0</truncated>
        <difficult>0</difficult>
        <bndbox>
            <xmin>1867.0</xmin>
            <ymin>1079.0</ymin>
            <xmax>1860.0</xmax>
            <ymax>1071.0</ymax>
        </bndbox>
    </object>
    <object>
        <name>Car</name>
        <pose>Unspecified</pose>
        <truncated>0</truncated>
        <difficult>0</difficult>
        <bndbox>
            <xmin>712.0</xmin>
            <ymin>663.0</ymin>
            <xmax>717.0</xmax>
            <ymax>646.0</ymax>
        </bndbox>
    </object>
    <object>
        <name>Car</name>
        <pose>Unspecified</pose>
        <truncated>0</truncated>
        <difficult>0</difficult>
        <bndbox>
            <xmin>1705.0</xmin>
            <ymin>0.0</ymin>
            <xmax>1721.0</xmax>
            <ymax>0.0</ymax>
        </bndbox>
    </object>
    <object>
        <name>Pedestrian</name>
        <pose>Unspecified</pose>
        <truncated>0</truncated>
        <difficult>0</difficult>
        <bndbox>
            <xmin>694.0</xmin>
            <ymin>373.0</ymin>
            <xmax>692.0</xmax>
            <ymax>376.0</ymax>
        </bndbox>
    </object>
    <object>
        <name>Car</name>
        <pose>Unspecified</pose>
        <truncated>0</truncated>
        <difficult>0</difficult>
        <bndbox>
            <xmin>1689.0</xmin>
            <ymin>347.0</ymin>
            <xmax>1699.0</xmax>
            <ymax>345.0</ymax>
        </bndbox>
    </object>
    <object>
        <name>Car</name>
        <pose>Unspecified</pose>
        <truncated>0</truncated>
        <difficult>0</difficult>
        <bndbox>
            <xmin>878.0</xmin>
            <ymin>284.0</ymin>
            <xmax>884.0</xmax>
            <ymax>277.0</ymax>
        </bndbox>
    </object>
    <object>
        <name>Car</name>
        <pose>Unspecified</pose>
        <truncated>0</truncated>
        <difficult>0</difficult>
        <bndbox>
            <xmin>1506.0</xmin>
            <ymin>300.0</ymin>
            <xmax>1514.0</xmax>
            <ymax>296.0</ymax>
        </bndbox>
    </object>
    <object>
        <name>Car</name>
        <pose>Unspecified</pose>
        <truncated>0</truncated>
        <difficult>0</difficult>
        <bndbox>
            <xmin>1788.0</xmin>
            <ymin>160.0</ymin>
            <xmax>1796.0</xmax>
            <ymax>156.0</ymax>
        </bndbox>
    </object>
</annotation>
